agilerl/__init__.py
agilerl/algorithms/__init__.py
agilerl/algorithms/bc_lm.py
agilerl/algorithms/core/__init__.py
agilerl/algorithms/core/base.py
agilerl/algorithms/core/optimizer_wrapper.py
agilerl/algorithms/core/registry.py
agilerl/algorithms/cqn.py
agilerl/algorithms/ddpg.py
agilerl/algorithms/dpo.py
agilerl/algorithms/dqn.py
agilerl/algorithms/dqn_rainbow.py
agilerl/algorithms/grpo.py
agilerl/algorithms/ilql.py
agilerl/algorithms/ippo.py
agilerl/algorithms/maddpg.py
agilerl/algorithms/matd3.py
agilerl/algorithms/neural_ts_bandit.py
agilerl/algorithms/neural_ucb_bandit.py
agilerl/algorithms/ppo.py
agilerl/algorithms/td3.py
agilerl/components/__init__.py
agilerl/components/data.py
agilerl/components/multi_agent_replay_buffer.py
agilerl/components/replay_buffer.py
agilerl/components/rollout_buffer.py
agilerl/components/sampler.py
agilerl/components/segment_tree.py
agilerl/data/__init__.py
agilerl/data/language_environment.py
agilerl/data/rl_data.py
agilerl/data/tokenizer.py
agilerl/data/torch_datasets.py
agilerl/hpo/__init__.py
agilerl/hpo/mutation.py
agilerl/hpo/tournament.py
agilerl/modules/__init__.py
agilerl/modules/base.py
agilerl/modules/bert.py
agilerl/modules/cnn.py
agilerl/modules/configs.py
agilerl/modules/custom_components.py
agilerl/modules/dummy.py
agilerl/modules/gpt.py
agilerl/modules/lstm.py
agilerl/modules/mlp.py
agilerl/modules/multi_input.py
agilerl/modules/resnet.py
agilerl/modules/simba.py
agilerl/networks/__init__.py
agilerl/networks/actors.py
agilerl/networks/base.py
agilerl/networks/custom_modules.py
agilerl/networks/distributions.py
agilerl/networks/distributions_experimental.py
agilerl/networks/q_networks.py
agilerl/networks/value_networks.py
agilerl/protocols.py
agilerl/rollouts/__init__.py
agilerl/rollouts/on_policy.py
agilerl/training/__init__.py
agilerl/training/train_bandits.py
agilerl/training/train_llm.py
agilerl/training/train_multi_agent_off_policy.py
agilerl/training/train_multi_agent_on_policy.py
agilerl-2.4.1.dist-info/METADATA
agilerl-2.4.1.dist-info/WHEEL
agilerl-2.4.1.dist-info/licenses/LICENSE
agilerl-2.4.1.dist-info/RECORD
