Metadata-Version: 2.4
Name: agilerl
Version: 2.4.1
Summary: AgileRL is a deep reinforcement learning library focused on improving RL development through RLOps.
License: Apache 2.0
License-File: LICENSE
Author: Nick Ustaran-Anderegg
Author-email: dev@agilerl.com
Requires-Python: >=3.10,<3.13
Classifier: License :: Other/Proprietary License
Classifier: Programming Language :: Python :: 3
Classifier: Programming Language :: Python :: 3.10
Classifier: Programming Language :: Python :: 3.11
Classifier: Programming Language :: Python :: 3.12
Provides-Extra: all
Provides-Extra: llm
Requires-Dist: SuperSuit (>=3.9.0,<4.0.0)
Requires-Dist: accelerate (>=1.7.0,<2.0.0)
Requires-Dist: datasets (==4.4.1) ; extra == "llm" or extra == "all"
Requires-Dist: deepspeed (>=0.17.1,<0.18.0) ; extra == "llm" or extra == "all"
Requires-Dist: dill (>=0.3.7,<0.4.0)
Requires-Dist: fastrand (>=1.3.0,<2.0.0)
Requires-Dist: flatten_dict (>=0.4.2,<0.5.0)
Requires-Dist: google-cloud-storage (>=2.5.0,<3.0.0)
Requires-Dist: gymnasium (>=1.0.0,<2.0.0)
Requires-Dist: h5py (>=3.8.0,<4.0.0)
Requires-Dist: hydra-core (>=1.3.2,<2.0.0)
Requires-Dist: jax[cpu] (>=0.4.31,<0.5.0)
Requires-Dist: matplotlib (>=3.9.4,<3.10.0)
Requires-Dist: minari[all] (==0.5.2)
Requires-Dist: numpy (>=1.26.4,<2.0.0)
Requires-Dist: omegaconf (>=2.3.0,<3.0.0)
Requires-Dist: packaging (>=20.0)
Requires-Dist: pandas (>=2.2.3,<3.0.0)
Requires-Dist: peft (>=0.18.0,<0.19.0) ; extra == "llm" or extra == "all"
Requires-Dist: pettingzoo (>=1.23.1,<2.0.0)
Requires-Dist: pre-commit (>=3.4.0,<4.0.0)
Requires-Dist: pygame (>=2.6.0,<3.0.0)
Requires-Dist: pymunk (>=6.2.0,<7.0.0)
Requires-Dist: redis (>=4.4.4,<5.0.0)
Requires-Dist: scipy (>=1.12.0,<2.0.0)
Requires-Dist: tensordict (>=0.8,<0.9)
Requires-Dist: termcolor (>=1.1.0,<2.0.0)
Requires-Dist: torch (==2.7.1)
Requires-Dist: tqdm (>=4.66.4,<5.0.0)
Requires-Dist: transformers (>=4.57.1,<5.0.0) ; extra == "llm" or extra == "all"
Requires-Dist: ucimlrepo (>=0.0.3,<0.0.4)
Requires-Dist: vllm (==0.10.0) ; extra == "llm" or extra == "all"
Requires-Dist: wandb (>=0.17.6,<0.18.0)
